hailin/__init__.py
hailin/_version.py
hailin/version.py
hailin/widgets/__init__.py
hailin/widgets/mplwidget.py
hailin-2023.3.29.dist-info/METADATA
hailin-2023.3.29.dist-info/WHEEL
hailin-2023.3.29.dist-info/top_level.txt
hailin-2023.3.29.dist-info/RECORD
